odoo/addons/pos_payment_terminal/README.rst
odoo/addons/pos_payment_terminal/__init__.py
odoo/addons/pos_payment_terminal/__manifest__.py
odoo/addons/pos_payment_terminal/i18n/es.po
odoo/addons/pos_payment_terminal/i18n/fr.po
odoo/addons/pos_payment_terminal/i18n/hr_HR.po
odoo/addons/pos_payment_terminal/i18n/it.po
odoo/addons/pos_payment_terminal/i18n/nl_NL.po
odoo/addons/pos_payment_terminal/i18n/pos_payment_terminal.pot
odoo/addons/pos_payment_terminal/models/__init__.py
odoo/addons/pos_payment_terminal/models/account_journal.py
odoo/addons/pos_payment_terminal/models/pos_config.py
odoo/addons/pos_payment_terminal/models/pos_order.py
odoo/addons/pos_payment_terminal/readme/CONFIGURE.rst
odoo/addons/pos_payment_terminal/readme/CONTRIBUTORS.rst
odoo/addons/pos_payment_terminal/readme/DESCRIPTION.rst
odoo/addons/pos_payment_terminal/readme/INSTALL.rst
odoo/addons/pos_payment_terminal/readme/USAGE.rst
odoo/addons/pos_payment_terminal/static/description/account_journal_form.png
odoo/addons/pos_payment_terminal/static/description/icon.png
odoo/addons/pos_payment_terminal/static/description/index.html
odoo/addons/pos_payment_terminal/static/description/pos_config.png
odoo/addons/pos_payment_terminal/static/src/css/pos_payment_terminal.css
odoo/addons/pos_payment_terminal/static/src/js/devices.js
odoo/addons/pos_payment_terminal/static/src/js/models.js
odoo/addons/pos_payment_terminal/static/src/js/screens.js
odoo/addons/pos_payment_terminal/static/src/xml/pos_payment_terminal.xml
odoo/addons/pos_payment_terminal/tests/__init__.py
odoo/addons/pos_payment_terminal/tests/test_transactions.py
odoo/addons/pos_payment_terminal/views/account_journal.xml
odoo/addons/pos_payment_terminal/views/assets.xml
odoo/addons/pos_payment_terminal/views/pos_config.xml
odoo12_addon_pos_payment_terminal-12.0.0.1.6.dist-info/METADATA
odoo12_addon_pos_payment_terminal-12.0.0.1.6.dist-info/WHEEL
odoo12_addon_pos_payment_terminal-12.0.0.1.6.dist-info/top_level.txt
odoo12_addon_pos_payment_terminal-12.0.0.1.6.dist-info/RECORD
